paramorph/__init__.py
paramorph/build.py
paramorph/constants.py
paramorph/core.py
paramorph/paramorph_callbacks.py
paramorph/paramorph_config.py
paramorph/paramorph_sdk.py
paramorph/utils.py
paramorph/huggingface/__init__.py
paramorph/huggingface/callbacks.py
paramorph/huggingface/trainer.py
paramorph/lightning/__init__.py
paramorph/lightning/lightning_module.py
paramorph-0.9.1.dist-info/licenses/LICENSE
paramorph-0.9.1.dist-info/METADATA
paramorph-0.9.1.dist-info/WHEEL
paramorph-0.9.1.dist-info/top_level.txt
paramorph-0.9.1.dist-info/RECORD
