Metadata-Version: 2.4
Name: paramorph
Version: 0.9.1
Summary: Inephany client library to use Paramorph Agents.
Author-email: Inephany <info@inephany.com>
License: Apache 2.0
Keywords: paramorph,agents,client
Classifier: Development Status :: 4 - Beta
Classifier: Intended Audience :: Developers
Classifier: Programming Language :: Python :: 3
Classifier: Programming Language :: Python :: 3.10
Classifier: Programming Language :: Python :: 3.11
Classifier: Programming Language :: Python :: 3.12
Requires-Python: >=3.10
License-File: LICENSE
Requires-Dist: torch<2.9.0,>=2.1.0
Requires-Dist: numpy<2.0.0,>=1.24.0
Requires-Dist: loguru<0.8.0,>=0.7.0
Requires-Dist: plotly<6.0.0,>=5.15.0
Requires-Dist: requests<3.0.0,>=2.28.0
Requires-Dist: pydantic<3.0.0,>=2.5.0
Requires-Dist: urllib3<3.0.0,>=2.0.0
Requires-Dist: PyYAML<7.0.0,>=6.0.0
Requires-Dist: libinephany<1.0.0,>=0.13.0
Provides-Extra: dev
Requires-Dist: pytest<9.0.0,>=7.0.0; extra == "dev"
Requires-Dist: pytest-mock<4.0.0,>=3.10.0; extra == "dev"
Requires-Dist: bump-my-version==0.11.0; extra == "dev"
Requires-Dist: black==24.4.2; extra == "dev"
Requires-Dist: isort==5.9.3; extra == "dev"
Requires-Dist: flake8==7.1.0; extra == "dev"
Requires-Dist: pre-commit==4.0.1; extra == "dev"
Requires-Dist: mypy==1.13.0; extra == "dev"
Requires-Dist: types-PyYAML>=6.0.12; extra == "dev"
Requires-Dist: types-redis>=4.5.0; extra == "dev"
Requires-Dist: types-requests>=2.28.0; extra == "dev"
Requires-Dist: types-cachetools>=6.1.0; extra == "dev"
Requires-Dist: typeguard==4.3.0; extra == "dev"
Requires-Dist: lightning<3.0.0,>=2.0.0; extra == "dev"
Provides-Extra: lightning
Requires-Dist: lightning<3.0.0,>=2.0.0; extra == "lightning"
Dynamic: license-file
